setup.cfg
setup.py
mud/__init__.py
mud/api/__init__.py
mud/api/constants.py
mud/api/structs.py
mud/api/tests.py
mud/lang/__init__.py
mud/lang/ql.py
mud/lang/document/__init__.py
mud/management/__init__.py
mud/management/config.py
mud/management/services.py
mud/management/syslog.py
mud/player/__init__.py
mud/player/events.py
mud/player/http.py
mud/player/shell.py
mud/player/commands/__init__.py
mud/player/commands/mime.py
mud/player/db/__init__.py
mud/player/db/managedfs.py
mud/player/db/rent/__init__.py
mud/player/db/rent/constants.py
mud/player/db/rent/edit.py
mud/player/db/rent/equip.py
mud/player/db/rent/management.py
mud/player/db/rent/scan.py
mud/player/db/rent/show.py
mud/player/interfaces/__init__.py
mud/player/interfaces/dictcmd.py
mud/player/interfaces/history.py
mud/player/interfaces/standard.py
mud/player/interfaces/threading.py
mud/player/interfaces/code/__init__.py
mud/player/interfaces/code/environ.py
mud/player/interfaces/code/python.py
mud/runtime/__init__.py
mud/runtime/core.py
mud/runtime/events.py
mud/runtime/facilities.py
mud/runtime/misc.py
mud/runtime/plugins.py
mud/runtime/registry.py
mud/runtime/sandbox.py
mud/runtime/structure.py
mud/runtime/support.py
mud/runtime/pentacle/__init__.py
mud/runtime/pentacle/oob.py
mud/runtime/pentacle/partner.py
mud/tasks/__init__.py
mud/tasks/heartbeat.py
mud/tasks/interactive.py
mud/tasks/scheduler.py
mud/tasks/virtual.py
mud/tasks/vtpool.py
mud/tools/__init__.py
mud/tools/cmdln.py
mud/tools/debugging.py
mud/tools/errors.py
mud/tools/internet.py
mud/tools/logs.py
mud/tools/misc.py
mud/tools/platform.py
mud/tools/pyg_colorizer.py
mud/tools/strings.py
mud/tools/timing.py
mud/zones/__init__.py
mud/zones/config.py
mud/zones/freeze.py
mud/zones/specials/__init__.py
mud/zones/specials/standard.py
stuphos_lite.egg-info/PKG-INFO
stuphos_lite.egg-info/SOURCES.txt
stuphos_lite.egg-info/dependency_links.txt
stuphos_lite.egg-info/top_level.txt