Metadata-Version: 1.1
Name: stuphos-lite
Version: 0.8
Summary: StuphOS embedded runtime configuration (lite release).
Home-page: http://stuphmud.net:2184
Author: Clint Banis
Author-email: cbanis@gmail.com
License: BSD
Download-URL: http://stuphmud.net:2184
Keywords: stuphos,stuphmud,stuph,mud,circlemud,circle
Platform: POSIX
Platform: Linux
Platform: Cygwin
Platform: OS-independent
Platform: Many
Classifier: Development Status :: 2 - Pre-Alpha
Classifier: Programming Language :: Python
Classifier: Programming Language :: Python :: 2
Classifier: Operating System :: OS Independent
Classifier: Topic :: Scientific/Engineering
Classifier: Topic :: Software Development :: Libraries :: Python Modules
Classifier: Topic :: Software Development :: Embedded Systems
Classifier: Topic :: Software Development :: Libraries :: Application Frameworks
Classifier: Topic :: System :: Networking
Classifier: Topic :: System :: Distributed Computing
Classifier: Topic :: System :: Systems Administration
Classifier: Topic :: Office/Business :: Groupware
Classifier: Topic :: Utilities
Classifier: Intended Audience :: System Administrators
Classifier: Intended Audience :: End Users/Desktop
Classifier: Intended Audience :: Science/Research
Classifier: Intended Audience :: Education
